vecsdk/__init__.py
vectorization_pb2.py
vectorization_pb2.pyi
vectorization_pb2_grpc.py
vecsdk-0.1.2.dist-info/METADATA
vecsdk-0.1.2.dist-info/WHEEL
vecsdk-0.1.2.dist-info/RECORD
