Metadata-Version: 2.1
Name: vecsdk
Version: 0.1.2
Summary: 
Author: znittzel
Author-email: rikard@ourstudio.se
Requires-Python: >=3.9,<4.0
Classifier: Programming Language :: Python :: 3
Classifier: Programming Language :: Python :: 3.9
Classifier: Programming Language :: Python :: 3.10
Classifier: Programming Language :: Python :: 3.11
Classifier: Programming Language :: Python :: 3.12
Classifier: Programming Language :: Python :: 3.13
Requires-Dist: grpcio (>=1.67.1,<2.0.0)
Requires-Dist: grpcio-tools (>=1.67.1,<2.0.0)
Requires-Dist: numpy (<2.0.0)
Requires-Dist: protobuf (>=5.28.3,<6.0.0)
